{"Index":"-","P/E":"-","EPS (ttm)":"-1.40","Insider Own":"-","Shs Outstand":"53.90M","Perf Week":"0.78%","Market Cap":"1.47B","Forward P/E":"-","EPS next Y":"-","Insider Trans":"-","Shs Float":"-","Perf Month":"3.89%","Income":"-","PEG":"-","EPS next Q":"-","Inst Own":"11.47%","Short Float":"-","Perf Quarter":"8.83%","Sales":"61.29M","P/S":"23.94","EPS this Y":"-","Inst Trans":"-","Short Ratio":"13.86","Perf Half Y":"10.80%","Book/sh":"26.58","P/B":"1.02","ROA":"-","Target Price":"-","Perf Year":"5.73%","Cash/sh":"-","P/C":"-","EPS next 5Y":"-","ROE":"-","52W Range":"21.83 - 27.33","Perf YTD":"15.77%","Dividend":"0.95","P/FCF":"-","EPS past 5Y":"-","ROI":"-","52W High":"-0.20%","Beta":"-","Dividend %":"3.49%","Quick Ratio":"-","Sales past 5Y":"-","Gross Margin":"-","52W Low":"24.94%","ATR":"0.18","Employees":"-","Current Ratio":"-","Sales Q/Q":"3.90%","Oper. Margin":"-","RSI (14)":"68.69","Volatility":"0.58% 0.54%","Optionable":"No","Debt/Eq":"-","EPS Q/Q":"-","Profit Margin":"-","Rel Volume":"1.64","Prev Close":"27.23","Shortable":"Yes","LT Debt/Eq":"-","Earnings":"-","Payout":"-","Avg Volume":"59.89K","Price":"27.27","Recom":"-","SMA20":"1.33%","SMA50":"2.85%","SMA200":"5.34%","Volume":"35,699","Change":"0.17%"}