{"Index":"S&P 500","P/E":"25.67","EPS (ttm)":"3.48","Insider Own":"0.50%","Shs Outstand":"563.87M","Perf Week":"-0.44%","Market Cap":"50.30B","Forward P/E":"21.32","EPS next Y":"10.57%","Insider Trans":"-13.36%","Shs Float":"554.41M","Perf Month":"2.08%","Income":"2.00B","PEG":"2.99","EPS next Q":"0.93","Inst Own":"92.50%","Short Float":"1.05%","Perf Quarter":"11.89%","Sales":"5.02B","P/S":"10.01","EPS this Y":"15.10%","Inst Trans":"0.16%","Short Ratio":"2.72","Perf Half Y":"16.21%","Book/sh":"30.12","P/B":"2.96","ROA":"2.30%","Target Price":"96.39","Perf Year":"20.69%","Cash/sh":"-","P/C":"-","EPS next 5Y":"8.60%","ROE":"11.80%","52W Range":"69.69 - 92.31","Perf YTD":"18.41%","Dividend":"1.10","P/FCF":"26.53","EPS past 5Y":"34.70%","ROI":"8.40%","52W High":"-3.66%","Beta":"0.50","Dividend %":"1.23%","Quick Ratio":"1.00","Sales past 5Y":"25.50%","Gross Margin":"-","52W Low":"27.61%","ATR":"1.40","Employees":"5161","Current Ratio":"1.00","Sales Q/Q":"3.70%","Oper. Margin":"51.70%","RSI (14)":"50.63","Volatility":"1.84% 1.47%","Optionable":"Yes","Debt/Eq":"0.44","EPS Q/Q":"7.20%","Profit Margin":"40.00%","Rel Volume":"0.94","Prev Close":"89.20","Shortable":"Yes","LT Debt/Eq":"0.38","Earnings":"Aug 01 BMO","Payout":"27.30%","Avg Volume":"2.15M","Price":"88.93","Recom":"1.90","SMA20":"-1.31%","SMA50":"2.41%","SMA200":"12.15%","Volume":"390,236","Change":"-0.30%"}