{"Index":"-","P/E":"-","EPS (ttm)":"-","Insider Own":"-","Shs Outstand":"66.14M","Perf Week":"1.01%","Market Cap":"462.98M","Forward P/E":"-","EPS next Y":"-","Insider Trans":"-","Shs Float":"-","Perf Month":"4.63%","Income":"-","PEG":"-","EPS next Q":"-","Inst Own":"38.03%","Short Float":"-","Perf Quarter":"5.90%","Sales":"-","P/S":"-","EPS this Y":"-","Inst Trans":"-","Short Ratio":"-","Perf Half Y":"9.03%","Book/sh":"-","P/B":"-","ROA":"-","Target Price":"-","Perf Year":"2.19%","Cash/sh":"-","P/C":"-","EPS next 5Y":"-","ROE":"-","52W Range":"5.91 - 7.11","Perf YTD":"15.51%","Dividend":"0.60","P/FCF":"-","EPS past 5Y":"-","ROI":"-","52W High":"-0.28%","Beta":"-","Dividend %":"8.57%","Quick Ratio":"-","Sales past 5Y":"-","Gross Margin":"-","52W Low":"19.97%","ATR":"0.09","Employees":"-","Current Ratio":"-","Sales Q/Q":"-","Oper. Margin":"-","RSI (14)":"73.62","Volatility":"0.89% 1.35%","Optionable":"No","Debt/Eq":"-","EPS Q/Q":"-","Profit Margin":"-","Rel Volume":"0.59","Prev Close":"7.00","Shortable":"Yes","LT Debt/Eq":"-","Earnings":"-","Payout":"-","Avg Volume":"222.38K","Price":"7.09","Recom":"-","SMA20":"2.76%","SMA50":"5.90%","SMA200":"7.87%","Volume":"26,161","Change":"1.29%"}