{"Index":"-","P/E":"-","EPS (ttm)":"-1.58","Insider Own":"0.30%","Shs Outstand":"51.74M","Perf Week":"-5.07%","Market Cap":"44.50M","Forward P/E":"-","EPS next Y":"-4.10%","Insider Trans":"-23.40%","Shs Float":"41.66M","Perf Month":"-13.19%","Income":"-65.20M","PEG":"-","EPS next Q":"-0.38","Inst Own":"60.50%","Short Float":"10.93%","Perf Quarter":"-20.37%","Sales":"6.90M","P/S":"6.45","EPS this Y":"31.30%","Inst Trans":"-0.06%","Short Ratio":"4.09","Perf Half Y":"-71.24%","Book/sh":"1.98","P/B":"0.43","ROA":"-64.70%","Target Price":"9.50","Perf Year":"-66.92%","Cash/sh":"2.04","P/C":"0.42","EPS next 5Y":"-","ROE":"-84.00%","52W Range":"0.86 - 10.38","Perf YTD":"-73.46%","Dividend":"-","P/FCF":"-","EPS past 5Y":"-6.30%","ROI":"-55.30%","52W High":"-91.96%","Beta":"-0.71","Dividend %":"-","Quick Ratio":"11.30","Sales past 5Y":"20.00%","Gross Margin":"-","52W Low":"-2.99%","ATR":"0.05","Employees":"48","Current Ratio":"11.30","Sales Q/Q":"455.60%","Oper. Margin":"-","RSI (14)":"30.82","Volatility":"5.99% 5.39%","Optionable":"Yes","Debt/Eq":"0.00","EPS Q/Q":"11.60%","Profit Margin":"-","Rel Volume":"1.07","Prev Close":"0.86","Shortable":"Yes","LT Debt/Eq":"0.00","Earnings":"Aug 07 AMC","Payout":"-","Avg Volume":"1.11M","Price":"0.83","Recom":"1.80","SMA20":"-12.70%","SMA50":"-16.85%","SMA200":"-71.84%","Volume":"219,763","Change":"-2.99%"}