{"Index":"-","P/E":"-","EPS (ttm)":"-3.71","Insider Own":"6.00%","Shs Outstand":"30.28M","Perf Week":"-4.18%","Market Cap":"263.74M","Forward P/E":"-","EPS next Y":"16.70%","Insider Trans":"-","Shs Float":"27.64M","Perf Month":"29.23%","Income":"-83.50M","PEG":"-","EPS next Q":"-0.89","Inst Own":"79.20%","Short Float":"3.58%","Perf Quarter":"-37.20%","Sales":"-","P/S":"-","EPS this Y":"-124.00%","Inst Trans":"1.83%","Short Ratio":"13.75","Perf Half Y":"-34.51%","Book/sh":"2.85","P/B":"3.06","ROA":"-78.30%","Target Price":"17.88","Perf Year":"-","Cash/sh":"3.30","P/C":"2.64","EPS next 5Y":"-","ROE":"-","52W Range":"6.23 - 19.00","Perf YTD":"-38.79%","Dividend":"-","P/FCF":"-","EPS past 5Y":"-","ROI":"-","52W High":"-52.79%","Beta":"-","Dividend %":"-","Quick Ratio":"8.70","Sales past 5Y":"-","Gross Margin":"-","52W Low":"43.98%","ATR":"0.82","Employees":"118","Current Ratio":"8.70","Sales Q/Q":"-","Oper. Margin":"-","RSI (14)":"51.11","Volatility":"6.49% 11.42%","Optionable":"No","Debt/Eq":"0.18","EPS Q/Q":"-5.60%","Profit Margin":"-","Rel Volume":"0.51","Prev Close":"8.71","Shortable":"Yes","LT Debt/Eq":"0.16","Earnings":"Aug 01","Payout":"-","Avg Volume":"71.91K","Price":"8.97","Recom":"2.00","SMA20":"0.67%","SMA50":"1.15%","SMA200":"-27.32%","Volume":"6,947","Change":"2.99%"}