{"Index":"-","P/E":"327.50","EPS (ttm)":"0.00","Insider Own":"-","Shs Outstand":"47.17M","Perf Week":"13.91%","Market Cap":"61.79M","Forward P/E":"-","EPS next Y":"-","Insider Trans":"-","Shs Float":"45.10M","Perf Month":"43.51%","Income":"-","PEG":"-","EPS next Q":"-","Inst Own":"-","Short Float":"0.53%","Perf Quarter":"101.85%","Sales":"12.72M","P/S":"4.86","EPS this Y":"-","Inst Trans":"-","Short Ratio":"2.62","Perf Half Y":"225.95%","Book/sh":"0.17","P/B":"7.57","ROA":"-","Target Price":"-","Perf Year":"125.45%","Cash/sh":"-","P/C":"-","EPS next 5Y":"-","ROE":"-","52W Range":"0.36 - 1.31","Perf YTD":"202.47%","Dividend":"-","P/FCF":"-","EPS past 5Y":"-","ROI":"-","52W High":"-1.02%","Beta":"-","Dividend %":"-","Quick Ratio":"-","Sales past 5Y":"-","Gross Margin":"-","52W Low":"261.07%","ATR":"0.08","Employees":"-","Current Ratio":"-","Sales Q/Q":"118.50%","Oper. Margin":"-","RSI (14)":"77.59","Volatility":"6.17% 7.43%","Optionable":"No","Debt/Eq":"-","EPS Q/Q":"-","Profit Margin":"-","Rel Volume":"2.52","Prev Close":"1.31","Shortable":"No","LT Debt/Eq":"-","Earnings":"Apr 01 BMO","Payout":"-","Avg Volume":"91.45K","Price":"1.30","Recom":"-","SMA20":"22.13%","SMA50":"52.62%","SMA200":"123.95%","Volume":"54,195","Change":"-1.02%"}