{"Index":"-","P/E":"-","EPS (ttm)":"-0.37","Insider Own":"0.90%","Shs Outstand":"35.45M","Perf Week":"5.54%","Market Cap":"2.60B","Forward P/E":"1221.67","EPS next Y":"119.40%","Insider Trans":"-31.04%","Shs Float":"34.94M","Perf Month":"-3.59%","Income":"-13.00M","PEG":"-","EPS next Q":"-0.11","Inst Own":"-","Short Float":"8.53%","Perf Quarter":"17.56%","Sales":"181.30M","P/S":"14.33","EPS this Y":"16.20%","Inst Trans":"-3.78%","Short Ratio":"7.82","Perf Half Y":"19.46%","Book/sh":"4.82","P/B":"15.21","ROA":"-7.10%","Target Price":"73.25","Perf Year":"132.55%","Cash/sh":"3.96","P/C":"18.49","EPS next 5Y":"32.60%","ROE":"-8.20%","52W Range":"31.09 - 83.14","Perf YTD":"30.50%","Dividend":"-","P/FCF":"302.15","EPS past 5Y":"2.90%","ROI":"-7.80%","52W High":"-13.40%","Beta":"1.55","Dividend %":"-","Quick Ratio":"5.40","Sales past 5Y":"54.00%","Gross Margin":"86.20%","52W Low":"131.56%","ATR":"2.84","Employees":"437","Current Ratio":"5.80","Sales Q/Q":"29.70%","Oper. Margin":"-7.20%","RSI (14)":"44.15","Volatility":"3.66% 3.60%","Optionable":"Yes","Debt/Eq":"0.00","EPS Q/Q":"69.70%","Profit Margin":"-7.10%","Rel Volume":"0.98","Prev Close":"73.30","Shortable":"Yes","LT Debt/Eq":"0.00","Earnings":"May 08 AMC","Payout":"-","Avg Volume":"381.46K","Price":"72.00","Recom":"2.00","SMA20":"-3.67%","SMA50":"-1.16%","SMA200":"18.82%","Volume":"142,813","Change":"-1.77%"}