{"Index":"-","P/E":"-","EPS (ttm)":"-0.34","Insider Own":"3.90%","Shs Outstand":"92.28M","Perf Week":"16.84%","Market Cap":"31.82M","Forward P/E":"-","EPS next Y":"42.10%","Insider Trans":"2.27%","Shs Float":"72.21M","Perf Month":"-10.14%","Income":"-27.90M","PEG":"-","EPS next Q":"-0.13","Inst Own":"55.90%","Short Float":"9.17%","Perf Quarter":"-45.30%","Sales":"77.60M","P/S":"0.41","EPS this Y":"88.20%","Inst Trans":"-6.12%","Short Ratio":"9.12","Perf Half Y":"-77.46%","Book/sh":"0.25","P/B":"1.38","ROA":"-5.90%","Target Price":"1.83","Perf Year":"-93.30%","Cash/sh":"0.08","P/C":"4.55","EPS next 5Y":"-","ROE":"-277.00%","52W Range":"0.28 - 5.54","Perf YTD":"-74.83%","Dividend":"-","P/FCF":"-","EPS past 5Y":"46.30%","ROI":"-17.40%","52W High":"-93.86%","Beta":"1.12","Dividend %":"-","Quick Ratio":"0.50","Sales past 5Y":"71.10%","Gross Margin":"73.90%","52W Low":"23.67%","ATR":"0.03","Employees":"39","Current Ratio":"0.50","Sales Q/Q":"23.40%","Oper. Margin":"-44.10%","RSI (14)":"49.42","Volatility":"6.82% 9.52%","Optionable":"Yes","Debt/Eq":"0.00","EPS Q/Q":"80.30%","Profit Margin":"-36.00%","Rel Volume":"0.30","Prev Close":"0.34","Shortable":"Yes","LT Debt/Eq":"5.39","Earnings":"Aug 09 BMO","Payout":"-","Avg Volume":"726.49K","Price":"0.34","Recom":"2.50","SMA20":"9.85%","SMA50":"-11.66%","SMA200":"-70.27%","Volume":"41,815","Change":"-1.36%"}