{"Index":"-","P/E":"14.87","EPS (ttm)":"0.95","Insider Own":"1.60%","Shs Outstand":"10.44M","Perf Week":"1.80%","Market Cap":"147.93M","Forward P/E":"13.28","EPS next Y":"18.29%","Insider Trans":"9.17%","Shs Float":"7.89M","Perf Month":"-4.58%","Income":"10.00M","PEG":"2.12","EPS next Q":"0.22","Inst Own":"45.70%","Short Float":"2.23%","Perf Quarter":"-15.15%","Sales":"56.40M","P/S":"2.62","EPS this Y":"60.40%","Inst Trans":"0.10%","Short Ratio":"12.45","Perf Half Y":"-9.63%","Book/sh":"14.99","P/B":"0.95","ROA":"-","Target Price":"16.33","Perf Year":"-31.55%","Cash/sh":"3.07","P/C":"4.62","EPS next 5Y":"7.00%","ROE":"-","52W Range":"13.26 - 20.93","Perf YTD":"-8.40%","Dividend":"0.36","P/FCF":"-","EPS past 5Y":"-0.50%","ROI":"27.00%","52W High":"-32.15%","Beta":"0.22","Dividend %":"2.54%","Quick Ratio":"-","Sales past 5Y":"7.70%","Gross Margin":"-","52W Low":"7.09%","ATR":"0.33","Employees":"156","Current Ratio":"-","Sales Q/Q":"3.50%","Oper. Margin":"-","RSI (14)":"42.93","Volatility":"1.26% 2.70%","Optionable":"Yes","Debt/Eq":"0.00","EPS Q/Q":"-71.20%","Profit Margin":"-","Rel Volume":"0.05","Prev Close":"14.17","Shortable":"Yes","LT Debt/Eq":"0.00","Earnings":"Jul 25 AMC","Payout":"-","Avg Volume":"14.12K","Price":"14.20","Recom":"3.00","SMA20":"1.24%","SMA50":"-5.66%","SMA200":"-8.60%","Volume":"150","Change":"0.21%"}