{"Index":"-","P/E":"-","EPS (ttm)":"-0.51","Insider Own":"2.00%","Shs Outstand":"23.48M","Perf Week":"1.73%","Market Cap":"456.92M","Forward P/E":"-","EPS next Y":"-18.20%","Insider Trans":"-23.45%","Shs Float":"22.60M","Perf Month":"-1.57%","Income":"-11.80M","PEG":"-","EPS next Q":"-0.09","Inst Own":"74.70%","Short Float":"1.39%","Perf Quarter":"4.85%","Sales":"136.30M","P/S":"3.35","EPS this Y":"1.50%","Inst Trans":"-13.73%","Short Ratio":"3.74","Perf Half Y":"18.44%","Book/sh":"4.52","P/B":"4.31","ROA":"-6.10%","Target Price":"25.50","Perf Year":"60.69%","Cash/sh":"1.58","P/C":"12.35","EPS next 5Y":"15.00%","ROE":"-9.10%","52W Range":"11.68 - 21.38","Perf YTD":"35.70%","Dividend":"-","P/FCF":"114.23","EPS past 5Y":"-12.40%","ROI":"-11.20%","52W High":"-9.07%","Beta":"0.57","Dividend %":"-","Quick Ratio":"1.30","Sales past 5Y":"6.30%","Gross Margin":"52.10%","52W Low":"66.44%","ATR":"0.47","Employees":"841","Current Ratio":"1.40","Sales Q/Q":"15.00%","Oper. Margin":"-8.50%","RSI (14)":"48.18","Volatility":"2.46% 2.54%","Optionable":"Yes","Debt/Eq":"0.00","EPS Q/Q":"-24.10%","Profit Margin":"-7.20%","Rel Volume":"0.21","Prev Close":"19.46","Shortable":"Yes","LT Debt/Eq":"0.00","Earnings":"May 23 AMC","Payout":"-","Avg Volume":"84.30K","Price":"19.44","Recom":"2.00","SMA20":"0.60%","SMA50":"-3.09%","SMA200":"13.55%","Volume":"4,319","Change":"-0.10%"}