{"Index":"-","P/E":"111.60","EPS (ttm)":"0.05","Insider Own":"-","Shs Outstand":"177.07M","Perf Week":"-3.63%","Market Cap":"988.06M","Forward P/E":"69.75","EPS next Y":"33.30%","Insider Trans":"-","Shs Float":"174.60M","Perf Month":"-10.14%","Income":"-","PEG":"-","EPS next Q":"0.01","Inst Own":"-","Short Float":"0.42%","Perf Quarter":"2.39%","Sales":"74.41M","P/S":"13.28","EPS this Y":"-64.70%","Inst Trans":"-","Short Ratio":"0.38","Perf Half Y":"-0.71%","Book/sh":"3.13","P/B":"1.78","ROA":"-","Target Price":"5.94","Perf Year":"46.07%","Cash/sh":"-","P/C":"-","EPS next 5Y":"-","ROE":"-","52W Range":"3.47 - 7.02","Perf YTD":"21.04%","Dividend":"-","P/FCF":"-","EPS past 5Y":"1.37%","ROI":"-","52W High":"-20.76%","Beta":"-","Dividend %":"-","Quick Ratio":"-","Sales past 5Y":"-","Gross Margin":"-","52W Low":"60.07%","ATR":"0.24","Employees":"23","Current Ratio":"-","Sales Q/Q":"13.50%","Oper. Margin":"-","RSI (14)":"33.99","Volatility":"3.64% 3.74%","Optionable":"Yes","Debt/Eq":"-","EPS Q/Q":"269.90%","Profit Margin":"-","Rel Volume":"2.48","Prev Close":"5.58","Shortable":"Yes","LT Debt/Eq":"-","Earnings":"Aug 21 AMC","Payout":"-","Avg Volume":"1.93M","Price":"5.56","Recom":"2.20","SMA20":"-8.58%","SMA50":"-9.77%","SMA200":"2.44%","Volume":"889,018","Change":"-0.31%"}