{"Index":"-","P/E":"-","EPS (ttm)":"-0.94","Insider Own":"91.84%","Shs Outstand":"93.28M","Perf Week":"5.90%","Market Cap":"786.35M","Forward P/E":"-","EPS next Y":"-","Insider Trans":"-","Shs Float":"7.55M","Perf Month":"-11.45%","Income":"-64.80M","PEG":"-","EPS next Q":"-","Inst Own":"0.60%","Short Float":"0.64%","Perf Quarter":"-89.76%","Sales":"193.40M","P/S":"4.07","EPS this Y":"-96.80%","Inst Trans":"20.70%","Short Ratio":"0.39","Perf Half Y":"-15.95%","Book/sh":"0.68","P/B":"12.40","ROA":"-23.40%","Target Price":"-","Perf Year":"-15.58%","Cash/sh":"0.23","P/C":"36.92","EPS next 5Y":"-","ROE":"-27.40%","52W Range":"6.28 - 310.90","Perf YTD":"-16.95%","Dividend":"-","P/FCF":"-","EPS past 5Y":"-","ROI":"-50.60%","52W High":"-97.36%","Beta":"-","Dividend %":"-","Quick Ratio":"0.90","Sales past 5Y":"-","Gross Margin":"64.40%","52W Low":"30.73%","ATR":"0.99","Employees":"700","Current Ratio":"1.10","Sales Q/Q":"19.70%","Oper. Margin":"-27.80%","RSI (14)":"48.48","Volatility":"10.20% 9.27%","Optionable":"No","Debt/Eq":"1.26","EPS Q/Q":"-620.30%","Profit Margin":"-33.50%","Rel Volume":"0.19","Prev Close":"8.43","Shortable":"No","LT Debt/Eq":"1.05","Earnings":"Mar 18 AMC","Payout":"-","Avg Volume":"125.00K","Price":"8.21","Recom":"-","SMA20":"-2.13%","SMA50":"-5.07%","SMA200":"-35.21%","Volume":"20,164","Change":"-2.61%"}