{"Index":"-","P/E":"16.80","EPS (ttm)":"1.21","Insider Own":"0.18%","Shs Outstand":"188.19M","Perf Week":"0.65%","Market Cap":"3.82B","Forward P/E":"14.16","EPS next Y":"9.82%","Insider Trans":"2.23%","Shs Float":"187.47M","Perf Month":"7.07%","Income":"231.00M","PEG":"3.38","EPS next Q":"0.33","Inst Own":"99.50%","Short Float":"3.26%","Perf Quarter":"10.94%","Sales":"2.32B","P/S":"1.65","EPS this Y":"-17.20%","Inst Trans":"0.09%","Short Ratio":"5.70","Perf Half Y":"-6.33%","Book/sh":"-1.58","P/B":"-","ROA":"12.10%","Target Price":"20.82","Perf Year":"-8.85%","Cash/sh":"0.61","P/C":"33.48","EPS next 5Y":"4.98%","ROE":"-69.90%","52W Range":"16.90 - 23.16","Perf YTD":"4.81%","Dividend":"0.42","P/FCF":"22.85","EPS past 5Y":"0.00%","ROI":"31.70%","52W High":"-11.87%","Beta":"-","Dividend %":"2.07%","Quick Ratio":"1.40","Sales past 5Y":"2.70%","Gross Margin":"34.10%","52W Low":"20.77%","ATR":"0.37","Employees":"6700","Current Ratio":"1.90","Sales Q/Q":"3.90%","Oper. Margin":"16.80%","RSI (14)":"66.81","Volatility":"1.60% 1.82%","Optionable":"Yes","Debt/Eq":"-","EPS Q/Q":"-0.50%","Profit Margin":"9.70%","Rel Volume":"0.43","Prev Close":"20.28","Shortable":"Yes","LT Debt/Eq":"-","Earnings":"Jul 31 AMC","Payout":"30.60%","Avg Volume":"1.07M","Price":"20.41","Recom":"2.40","SMA20":"1.60%","SMA50":"6.94%","SMA200":"4.96%","Volume":"83,535","Change":"0.64%"}