{"Index":"-","P/E":"17.05","EPS (ttm)":"39.37","Insider Own":"3.90%","Shs Outstand":"7.70M","Perf Week":"-1.32%","Market Cap":"5.17B","Forward P/E":"-","EPS next Y":"-","Insider Trans":"2.23%","Shs Float":"7.41M","Perf Month":"-11.99%","Income":"305.90M","PEG":"-","EPS next Q":"-","Inst Own":"40.60%","Short Float":"0.30%","Perf Quarter":"-22.53%","Sales":"431.50M","P/S":"11.98","EPS this Y":"117.80%","Inst Trans":"0.26%","Short Ratio":"1.78","Perf Half Y":"-10.43%","Book/sh":"43.02","P/B":"15.60","ROA":"77.20%","Target Price":"-","Perf Year":"-13.68%","Cash/sh":"22.69","P/C":"29.58","EPS next 5Y":"-","ROE":"90.60%","52W Range":"406.61 - 915.66","Perf YTD":"24.65%","Dividend":"1.75","P/FCF":"34.34","EPS past 5Y":"53.50%","ROI":"85.30%","52W High":"-26.70%","Beta":"1.29","Dividend %":"0.26%","Quick Ratio":"-","Sales past 5Y":"46.80%","Gross Margin":"-","52W Low":"65.07%","ATR":"27.69","Employees":"71","Current Ratio":"-","Sales Q/Q":"218.80%","Oper. Margin":"60.40%","RSI (14)":"40.49","Volatility":"4.16% 4.07%","Optionable":"No","Debt/Eq":"0.00","EPS Q/Q":"222.10%","Profit Margin":"48.60%","Rel Volume":"0.63","Prev Close":"657.79","Shortable":"Yes","LT Debt/Eq":"0.00","Earnings":"Aug 06 AMC","Payout":"3.90%","Avg Volume":"12.46K","Price":"671.17","Recom":"-","SMA20":"-5.82%","SMA50":"-10.39%","SMA200":"-6.03%","Volume":"7,858","Change":"2.03%"}