{"Index":"S&P 500","P/E":"29.59","EPS (ttm)":"6.45","Insider Own":"0.40%","Shs Outstand":"190.40M","Perf Week":"2.13%","Market Cap":"36.33B","Forward P/E":"21.62","EPS next Y":"10.40%","Insider Trans":"-23.20%","Shs Float":"188.66M","Perf Month":"3.98%","Income":"1.25B","PEG":"2.67","EPS next Q":"2.00","Inst Own":"96.40%","Short Float":"1.92%","Perf Quarter":"9.94%","Sales":"4.46B","P/S":"8.15","EPS this Y":"0.20%","Inst Trans":"0.22%","Short Ratio":"4.09","Perf Half Y":"30.92%","Book/sh":"0.65","P/B":"293.57","ROA":"14.50%","Target Price":"196.58","Perf Year":"7.31%","Cash/sh":"6.88","P/C":"27.72","EPS next 5Y":"11.10%","ROE":"427.20%","52W Range":"129.26 - 197.73","Perf YTD":"36.26%","Dividend":"2.00","P/FCF":"36.56","EPS past 5Y":"12.30%","ROI":"23.80%","52W High":"-3.26%","Beta":"1.27","Dividend %":"1.05%","Quick Ratio":"1.40","Sales past 5Y":"8.40%","Gross Margin":"71.50%","52W Low":"47.98%","ATR":"3.93","Employees":"13237","Current Ratio":"1.40","Sales Q/Q":"1.40%","Oper. Margin":"41.30%","RSI (14)":"55.91","Volatility":"1.62% 1.85%","Optionable":"Yes","Debt/Eq":"45.03","EPS Q/Q":"0.90%","Profit Margin":"29.40%","Rel Volume":"0.49","Prev Close":"190.82","Shortable":"Yes","LT Debt/Eq":"42.44","Earnings":"Apr 24 BMO","Payout":"26.60%","Avg Volume":"887.31K","Price":"191.28","Recom":"2.60","SMA20":"2.24%","SMA50":"1.32%","SMA200":"14.00%","Volume":"225,601","Change":"0.24%"}