{"Index":"-","P/E":"10.36","EPS (ttm)":"9.19","Insider Own":"-","Shs Outstand":"7.15M","Perf Week":"10.04%","Market Cap":"679.78M","Forward P/E":"-","EPS next Y":"-","Insider Trans":"-","Shs Float":"6.60M","Perf Month":"4.39%","Income":"-","PEG":"-","EPS next Q":"-","Inst Own":"84.68%","Short Float":"-","Perf Quarter":"-8.83%","Sales":"561.48M","P/S":"1.21","EPS this Y":"-","Inst Trans":"-","Short Ratio":"-","Perf Half Y":"15.28%","Book/sh":"74.89","P/B":"1.27","ROA":"-","Target Price":"-","Perf Year":"-12.27%","Cash/sh":"-","P/C":"-","EPS next 5Y":"-","ROE":"-","52W Range":"66.63 - 109.66","Perf YTD":"25.34%","Dividend":"7.25","P/FCF":"-","EPS past 5Y":"-","ROI":"-","52W High":"-13.26%","Beta":"-","Dividend %":"7.62%","Quick Ratio":"-","Sales past 5Y":"-","Gross Margin":"-","52W Low":"42.75%","ATR":"1.68","Employees":"577","Current Ratio":"-","Sales Q/Q":"5.70%","Oper. Margin":"-","RSI (14)":"62.90","Volatility":"0.65% 1.23%","Optionable":"No","Debt/Eq":"-","EPS Q/Q":"16.70%","Profit Margin":"-","Rel Volume":"0.16","Prev Close":"95.12","Shortable":"Yes","LT Debt/Eq":"-","Earnings":"-","Payout":"-","Avg Volume":"8.27K","Price":"95.12","Recom":"-","SMA20":"5.92%","SMA50":"3.28%","SMA200":"5.36%","Volume":"0","Change":"0.00%"}