{"Index":"-","P/E":"27.06","EPS (ttm)":"0.70","Insider Own":"0.04%","Shs Outstand":"31.60M","Perf Week":"-2.46%","Market Cap":"600.98M","Forward P/E":"-","EPS next Y":"-","Insider Trans":"-","Shs Float":"-","Perf Month":"-1.60%","Income":"-","PEG":"-","EPS next Q":"-","Inst Own":"10.34%","Short Float":"-","Perf Quarter":"1.39%","Sales":"54.66M","P/S":"10.99","EPS this Y":"-","Inst Trans":"-","Short Ratio":"-","Perf Half Y":"4.68%","Book/sh":"17.88","P/B":"1.06","ROA":"-","Target Price":"-","Perf Year":"2.20%","Cash/sh":"-","P/C":"-","EPS next 5Y":"-","ROE":"-","52W Range":"14.53 - 19.61","Perf YTD":"20.08%","Dividend":"1.47","P/FCF":"-","EPS past 5Y":"-","ROI":"-","52W High":"-3.64%","Beta":"-","Dividend %":"7.73%","Quick Ratio":"-","Sales past 5Y":"-","Gross Margin":"-","52W Low":"30.08%","ATR":"0.15","Employees":"-","Current Ratio":"-","Sales Q/Q":"-6.20%","Oper. Margin":"-","RSI (14)":"32.57","Volatility":"1.18% 0.70%","Optionable":"No","Debt/Eq":"-","EPS Q/Q":"-","Profit Margin":"-","Rel Volume":"1.14","Prev Close":"19.02","Shortable":"No","LT Debt/Eq":"-","Earnings":"-","Payout":"-","Avg Volume":"57.23K","Price":"18.90","Recom":"-","SMA20":"-2.33%","SMA50":"-1.59%","SMA200":"3.49%","Volume":"12,454","Change":"-0.63%"}