{"Index":"-","P/E":"-","EPS (ttm)":"-","Insider Own":"0.01%","Shs Outstand":"24.00M","Perf Week":"0.19%","Market Cap":"250.36M","Forward P/E":"-","EPS next Y":"-","Insider Trans":"-","Shs Float":"-","Perf Month":"1.07%","Income":"-","PEG":"-","EPS next Q":"-","Inst Own":"19.79%","Short Float":"-","Perf Quarter":"1.66%","Sales":"-","P/S":"-","EPS this Y":"-","Inst Trans":"-","Short Ratio":"-","Perf Half Y":"3.57%","Book/sh":"-","P/B":"-","ROA":"-","Target Price":"-","Perf Year":"4.93%","Cash/sh":"-","P/C":"-","EPS next 5Y":"-","ROE":"-","52W Range":"9.80 - 10.80","Perf YTD":"5.04%","Dividend":"0.60","P/FCF":"-","EPS past 5Y":"-","ROI":"-","52W High":"-3.25%","Beta":"-","Dividend %":"5.75%","Quick Ratio":"-","Sales past 5Y":"-","Gross Margin":"-","52W Low":"6.57%","ATR":"0.06","Employees":"-","Current Ratio":"-","Sales Q/Q":"-","Oper. Margin":"-","RSI (14)":"61.17","Volatility":"0.42% 0.46%","Optionable":"No","Debt/Eq":"-","EPS Q/Q":"-","Profit Margin":"-","Rel Volume":"0.74","Prev Close":"10.43","Shortable":"Yes","LT Debt/Eq":"-","Earnings":"-","Payout":"-","Avg Volume":"49.16K","Price":"10.44","Recom":"-","SMA20":"0.69%","SMA50":"0.83%","SMA200":"2.72%","Volume":"7,042","Change":"0.13%"}