{"Index":"-","P/E":"21.54","EPS (ttm)":"1.54","Insider Own":"4.50%","Shs Outstand":"2.70M","Perf Week":"-7.98%","Market Cap":"89.40M","Forward P/E":"-","EPS next Y":"-","Insider Trans":"2.93%","Shs Float":"2.25M","Perf Month":"6.12%","Income":"4.00M","PEG":"-","EPS next Q":"-","Inst Own":"6.90%","Short Float":"0.08%","Perf Quarter":"7.50%","Sales":"34.50M","P/S":"2.59","EPS this Y":"-52.50%","Inst Trans":"4.49%","Short Ratio":"0.86","Perf Half Y":"6.12%","Book/sh":"28.86","P/B":"1.15","ROA":"0.50%","Target Price":"-","Perf Year":"-5.56%","Cash/sh":"7.33","P/C":"4.52","EPS next 5Y":"-","ROE":"6.00%","52W Range":"28.67 - 38.70","Perf YTD":"9.13%","Dividend":"1.16","P/FCF":"30.83","EPS past 5Y":"-10.60%","ROI":"18.30%","52W High":"-14.44%","Beta":"0.46","Dividend %":"3.50%","Quick Ratio":"-","Sales past 5Y":"9.60%","Gross Margin":"-","52W Low":"15.49%","ATR":"1.73","Employees":"164","Current Ratio":"-","Sales Q/Q":"28.60%","Oper. Margin":"70.60%","RSI (14)":"50.67","Volatility":"3.40% 3.55%","Optionable":"No","Debt/Eq":"0.45","EPS Q/Q":"29.50%","Profit Margin":"12.00%","Rel Volume":"0.59","Prev Close":"33.11","Shortable":"Yes","LT Debt/Eq":"0.41","Earnings":"Aug 02 AMC","Payout":"62.20%","Avg Volume":"1.96K","Price":"33.11","Recom":"-","SMA20":"-0.18%","SMA50":"2.71%","SMA200":"1.40%","Volume":"0","Change":"0.00%"}