{"Index":"S&P 500","P/E":"39.56","EPS (ttm)":"8.91","Insider Own":"1.90%","Shs Outstand":"102.04M","Perf Week":"0.79%","Market Cap":"35.97B","Forward P/E":"26.74","EPS next Y":"4.05%","Insider Trans":"-1.44%","Shs Float":"101.27M","Perf Month":"5.04%","Income":"930.30M","PEG":"13.19","EPS next Q":"3.08","Inst Own":"94.90%","Short Float":"1.29%","Perf Quarter":"24.49%","Sales":"5.19B","P/S":"6.93","EPS this Y":"22.00%","Inst Trans":"0.03%","Short Ratio":"3.14","Perf Half Y":"29.80%","Book/sh":"74.99","P/B":"4.70","ROA":"7.50%","Target Price":"351.67","Perf Year":"31.61%","Cash/sh":"3.57","P/C":"98.70","EPS next 5Y":"3.00%","ROE":"15.20%","52W Range":"245.59 - 363.85","Perf YTD":"32.25%","Dividend":"1.85","P/FCF":"31.98","EPS past 5Y":"10.70%","ROI":"8.80%","52W High":"-2.40%","Beta":"1.20","Dividend %":"0.52%","Quick Ratio":"1.00","Sales past 5Y":"9.90%","Gross Margin":"63.20%","52W Low":"44.60%","ATR":"5.77","Employees":"15611","Current Ratio":"1.10","Sales Q/Q":"12.20%","Oper. Margin":"26.30%","RSI (14)":"69.08","Volatility":"2.50% 1.52%","Optionable":"Yes","Debt/Eq":"0.64","EPS Q/Q":"6.90%","Profit Margin":"21.80%","Rel Volume":"1.02","Prev Close":"352.48","Shortable":"Yes","LT Debt/Eq":"0.64","Earnings":"Apr 25 BMO","Payout":"14.40%","Avg Volume":"415.91K","Price":"355.13","Recom":"2.10","SMA20":"2.14%","SMA50":"6.58%","SMA200":"18.64%","Volume":"155,836","Change":"0.75%"}