{"Index":"S&P 500","P/E":"14.88","EPS (ttm)":"3.74","Insider Own":"2.80%","Shs Outstand":"119.53M","Perf Week":"1.15%","Market Cap":"6.64B","Forward P/E":"13.14","EPS next Y":"7.09%","Insider Trans":"-2.19%","Shs Float":"115.20M","Perf Month":"-1.09%","Income":"449.50M","PEG":"2.36","EPS next Q":"0.98","Inst Own":"97.78%","Short Float":"9.41%","Perf Quarter":"-16.59%","Sales":"5.87B","P/S":"1.13","EPS this Y":"35.40%","Inst Trans":"2.42%","Short Ratio":"8.87","Perf Half Y":"-4.83%","Book/sh":"9.20","P/B":"6.04","ROA":"22.20%","Target Price":"61.09","Perf Year":"-20.53%","Cash/sh":"2.26","P/C":"24.64","EPS next 5Y":"6.30%","ROE":"41.00%","52W Range":"52.79 - 79.91","Perf YTD":"-2.85%","Dividend":"1.24","P/FCF":"16.75","EPS past 5Y":"14.50%","ROI":"40.80%","52W High":"-28.95%","Beta":"1.32","Dividend %":"2.23%","Quick Ratio":"1.70","Sales past 5Y":"6.40%","Gross Margin":"41.60%","52W Low":"7.56%","ATR":"1.22","Employees":"18900","Current Ratio":"1.70","Sales Q/Q":"5.20%","Oper. Margin":"10.20%","RSI (14)":"47.79","Volatility":"1.94% 1.97%","Optionable":"Yes","Debt/Eq":"0.00","EPS Q/Q":"15.30%","Profit Margin":"7.60%","Rel Volume":"0.57","Prev Close":"55.57","Shortable":"Yes","LT Debt/Eq":"0.00","Earnings":"Jul 23 AMC","Payout":"30.60%","Avg Volume":"1.22M","Price":"56.78","Recom":"3.20","SMA20":"2.31%","SMA50":"-4.88%","SMA200":"-9.82%","Volume":"73,813","Change":"2.18%"}