{"Index":"-","P/E":"2.37","EPS (ttm)":"13.11","Insider Own":"0.30%","Shs Outstand":"52.50M","Perf Week":"0.45%","Market Cap":"1.63B","Forward P/E":"8.07","EPS next Y":"-31.14%","Insider Trans":"-95.40%","Shs Float":"51.31M","Perf Month":"2.85%","Income":"694.00M","PEG":"-","EPS next Q":"1.76","Inst Own":"-","Short Float":"14.60%","Perf Quarter":"14.46%","Sales":"1.38B","P/S":"1.18","EPS this Y":"66.30%","Inst Trans":"0.07%","Short Ratio":"10.81","Perf Half Y":"12.31%","Book/sh":"13.57","P/B":"2.29","ROA":"57.70%","Target Price":"33.91","Perf Year":"35.70%","Cash/sh":"4.25","P/C":"7.30","EPS next 5Y":"-","ROE":"140.90%","52W Range":"20.88 - 32.51","Perf YTD":"28.66%","Dividend":"0.20","P/FCF":"8.58","EPS past 5Y":"-","ROI":"61.90%","52W High":"-4.58%","Beta":"-","Dividend %":"0.64%","Quick Ratio":"3.30","Sales past 5Y":"-","Gross Margin":"47.30%","52W Low":"48.56%","ATR":"0.86","Employees":"412","Current Ratio":"3.80","Sales Q/Q":"50.30%","Oper. Margin":"36.90%","RSI (14)":"55.33","Volatility":"3.37% 2.66%","Optionable":"Yes","Debt/Eq":"0.66","EPS Q/Q":"536.70%","Profit Margin":"50.60%","Rel Volume":"1.20","Prev Close":"30.99","Shortable":"Yes","LT Debt/Eq":"0.66","Earnings":"May 01 AMC","Payout":"1.50%","Avg Volume":"692.89K","Price":"31.02","Recom":"2.20","SMA20":"0.76%","SMA50":"5.24%","SMA200":"16.90%","Volume":"834,514","Change":"0.10%"}