{"Index":"-","P/E":"-","EPS (ttm)":"-0.50","Insider Own":"34.30%","Shs Outstand":"9.27M","Perf Week":"12.60%","Market Cap":"53.96M","Forward P/E":"-","EPS next Y":"-","Insider Trans":"-","Shs Float":"6.33M","Perf Month":"3.22%","Income":"-","PEG":"-","EPS next Q":"-","Inst Own":"0.20%","Short Float":"0.05%","Perf Quarter":"-9.75%","Sales":"-","P/S":"-","EPS this Y":"-131.90%","Inst Trans":"-","Short Ratio":"0.36","Perf Half Y":"-","Book/sh":"0.77","P/B":"7.56","ROA":"-","Target Price":"-","Perf Year":"-","Cash/sh":"0.56","P/C":"10.38","EPS next 5Y":"-","ROE":"-","52W Range":"4.51 - 13.88","Perf YTD":"-31.75%","Dividend":"-","P/FCF":"-","EPS past 5Y":"-","ROI":"-","52W High":"-58.06%","Beta":"-","Dividend %":"-","Quick Ratio":"59.80","Sales past 5Y":"-","Gross Margin":"-","52W Low":"29.08%","ATR":"0.48","Employees":"2","Current Ratio":"59.80","Sales Q/Q":"-","Oper. Margin":"-","RSI (14)":"57.13","Volatility":"11.56% 8.20%","Optionable":"No","Debt/Eq":"0.00","EPS Q/Q":"34.30%","Profit Margin":"-","Rel Volume":"4.73","Prev Close":"5.05","Shortable":"Yes","LT Debt/Eq":"0.00","Earnings":"-","Payout":"-","Avg Volume":"9.42K","Price":"5.82","Recom":"-","SMA20":"8.59%","SMA50":"8.86%","SMA200":"3.85%","Volume":"44,496","Change":"15.27%"}