{"Index":"-","P/E":"-","EPS (ttm)":"-0.31","Insider Own":"1.00%","Shs Outstand":"10.98M","Perf Week":"2.16%","Market Cap":"20.75M","Forward P/E":"-","EPS next Y":"-","Insider Trans":"8.39%","Shs Float":"9.95M","Perf Month":"-6.82%","Income":"-3.60M","PEG":"-","EPS next Q":"-","Inst Own":"7.00%","Short Float":"0.08%","Perf Quarter":"-37.00%","Sales":"10.50M","P/S":"1.98","EPS this Y":"-385.10%","Inst Trans":"0.52%","Short Ratio":"0.83","Perf Half Y":"-37.21%","Book/sh":"1.27","P/B":"1.49","ROA":"-20.50%","Target Price":"15.55","Perf Year":"-31.99%","Cash/sh":"0.52","P/C":"3.64","EPS next 5Y":"-","ROE":"-22.70%","52W Range":"1.72 - 3.71","Perf YTD":"-35.22%","Dividend":"-","P/FCF":"-","EPS past 5Y":"-49.80%","ROI":"-10.50%","52W High":"-51.42%","Beta":"-0.06","Dividend %":"-","Quick Ratio":"11.90","Sales past 5Y":"-12.10%","Gross Margin":"27.40%","52W Low":"4.65%","ATR":"0.08","Employees":"54","Current Ratio":"14.00","Sales Q/Q":"-46.90%","Oper. Margin":"-34.60%","RSI (14)":"40.26","Volatility":"2.33% 3.43%","Optionable":"No","Debt/Eq":"0.00","EPS Q/Q":"-367.00%","Profit Margin":"-35.90%","Rel Volume":"0.07","Prev Close":"1.89","Shortable":"Yes","LT Debt/Eq":"0.00","Earnings":"Aug 19 BMO","Payout":"-","Avg Volume":"9.40K","Price":"1.80","Recom":"-","SMA20":"-7.83%","SMA50":"-10.77%","SMA200":"-34.30%","Volume":"123","Change":"-4.76%"}