{"Index":"-","P/E":"26.18","EPS (ttm)":"0.88","Insider Own":"0.05%","Shs Outstand":"26.03M","Perf Week":"1.28%","Market Cap":"596.33M","Forward P/E":"-","EPS next Y":"-","Insider Trans":"-","Shs Float":"-","Perf Month":"-0.26%","Income":"-","PEG":"-","EPS next Q":"-","Inst Own":"8.73%","Short Float":"-","Perf Quarter":"5.48%","Sales":"51.08M","P/S":"11.67","EPS this Y":"-","Inst Trans":"-","Short Ratio":"-","Perf Half Y":"11.81%","Book/sh":"20.40","P/B":"1.12","ROA":"-","Target Price":"-","Perf Year":"8.53%","Cash/sh":"-","P/C":"-","EPS next 5Y":"-","ROE":"-","52W Range":"17.02 - 23.22","Perf YTD":"21.60%","Dividend":"1.68","P/FCF":"-","EPS past 5Y":"-","ROI":"-","52W High":"-1.38%","Beta":"-","Dividend %":"7.33%","Quick Ratio":"-","Sales past 5Y":"-","Gross Margin":"-","52W Low":"34.55%","ATR":"0.21","Employees":"-","Current Ratio":"-","Sales Q/Q":"-6.50%","Oper. Margin":"-","RSI (14)":"55.17","Volatility":"0.67% 0.91%","Optionable":"No","Debt/Eq":"-","EPS Q/Q":"-","Profit Margin":"-","Rel Volume":"1.51","Prev Close":"22.91","Shortable":"Yes","LT Debt/Eq":"-","Earnings":"-","Payout":"-","Avg Volume":"87.41K","Price":"22.90","Recom":"-","SMA20":"0.70%","SMA50":"0.75%","SMA200":"6.68%","Volume":"30,078","Change":"-0.04%"}