{"Index":"S&P 500","P/E":"-","EPS (ttm)":"-4.40","Insider Own":"0.70%","Shs Outstand":"458.24M","Perf Week":"-1.62%","Market Cap":"10.29B","Forward P/E":"14.16","EPS next Y":"25.08%","Insider Trans":"1.62%","Shs Float":"445.43M","Perf Month":"-8.36%","Income":"-1984.00M","PEG":"-","EPS next Q":"0.35","Inst Own":"87.80%","Short Float":"2.35%","Perf Quarter":"-4.59%","Sales":"12.34B","P/S":"0.83","EPS this Y":"-772.00%","Inst Trans":"1.16%","Short Ratio":"2.54","Perf Half Y":"-4.55%","Book/sh":"22.98","P/B":"0.98","ROA":"-7.70%","Target Price":"29.87","Perf Year":"-32.31%","Cash/sh":"10.88","P/C":"2.06","EPS next 5Y":"27.60%","ROE":"-17.20%","52W Range":"18.20 - 34.39","Perf YTD":"14.71%","Dividend":"0.52","P/FCF":"-","EPS past 5Y":"-","ROI":"-11.30%","52W High":"-34.69%","Beta":"-","Dividend %":"2.32%","Quick Ratio":"1.00","Sales past 5Y":"-","Gross Margin":"17.70%","52W Low":"23.41%","ATR":"0.60","Employees":"37000","Current Ratio":"1.20","Sales Q/Q":"-6.80%","Oper. Margin":"-11.00%","RSI (14)":"39.14","Volatility":"2.70% 2.54%","Optionable":"Yes","Debt/Eq":"0.38","EPS Q/Q":"-77.40%","Profit Margin":"-16.20%","Rel Volume":"0.67","Prev Close":"22.97","Shortable":"Yes","LT Debt/Eq":"0.36","Earnings":"Apr 25 AMC","Payout":"-","Avg Volume":"4.12M","Price":"22.46","Recom":"2.10","SMA20":"-5.30%","SMA50":"-4.90%","SMA200":"-11.17%","Volume":"2,758,972","Change":"-2.22%"}