{"Index":"-","P/E":"-","EPS (ttm)":"-1.03","Insider Own":"6.56%","Shs Outstand":"94.44M","Perf Week":"-0.45%","Market Cap":"105.30M","Forward P/E":"-","EPS next Y":"41.80%","Insider Trans":"-","Shs Float":"94.44M","Perf Month":"-4.70%","Income":"-81.60M","PEG":"-","EPS next Q":"-0.11","Inst Own":"31.70%","Short Float":"4.64%","Perf Quarter":"-51.94%","Sales":"-","P/S":"-","EPS this Y":"51.00%","Inst Trans":"52.72%","Short Ratio":"2.01","Perf Half Y":"20.03%","Book/sh":"0.19","P/B":"5.87","ROA":"-70.30%","Target Price":"3.58","Perf Year":"-51.31%","Cash/sh":"0.69","P/C":"1.62","EPS next 5Y":"-","ROE":"-220.50%","52W Range":"0.66 - 2.60","Perf YTD":"-21.48%","Dividend":"-","P/FCF":"-","EPS past 5Y":"49.20%","ROI":"-","52W High":"-58.08%","Beta":"0.74","Dividend %":"-","Quick Ratio":"8.50","Sales past 5Y":"-","Gross Margin":"-","52W Low":"64.93%","ATR":"0.06","Employees":"17","Current Ratio":"8.50","Sales Q/Q":"-","Oper. Margin":"-","RSI (14)":"44.41","Volatility":"5.29% 4.88%","Optionable":"Yes","Debt/Eq":"0.00","EPS Q/Q":"-323.90%","Profit Margin":"-","Rel Volume":"1.03","Prev Close":"1.12","Shortable":"Yes","LT Debt/Eq":"0.00","Earnings":"Aug 13 BMO","Payout":"-","Avg Volume":"2.17M","Price":"1.09","Recom":"1.70","SMA20":"-3.30%","SMA50":"-9.29%","SMA200":"-11.14%","Volume":"416,427","Change":"-2.24%"}