{"Index":"-","P/E":"7.03","EPS (ttm)":"1.38","Insider Own":"0.44%","Shs Outstand":"13.02M","Perf Week":"-1.02%","Market Cap":"126.06M","Forward P/E":"-","EPS next Y":"-","Insider Trans":"-","Shs Float":"-","Perf Month":"-0.72%","Income":"-","PEG":"-","EPS next Q":"-","Inst Own":"40.20%","Short Float":"-","Perf Quarter":"2.00%","Sales":"3.84M","P/S":"32.82","EPS this Y":"-","Inst Trans":"-","Short Ratio":"0.21","Perf Half Y":"4.99%","Book/sh":"11.07","P/B":"0.87","ROA":"-","Target Price":"-","Perf Year":"2.33%","Cash/sh":"-","P/C":"-","EPS next 5Y":"-","ROE":"-","52W Range":"7.59 - 10.58","Perf YTD":"12.69%","Dividend":"0.48","P/FCF":"-","EPS past 5Y":"-","ROI":"-","52W High":"-7.94%","Beta":"-","Dividend %":"4.96%","Quick Ratio":"-","Sales past 5Y":"-","Gross Margin":"-","52W Low":"28.33%","ATR":"0.12","Employees":"-","Current Ratio":"-","Sales Q/Q":"-3.40%","Oper. Margin":"-","RSI (14)":"48.77","Volatility":"1.76% 1.21%","Optionable":"No","Debt/Eq":"-","EPS Q/Q":"111.00%","Profit Margin":"-","Rel Volume":"0.58","Prev Close":"9.68","Shortable":"No","LT Debt/Eq":"-","Earnings":"-","Payout":"-","Avg Volume":"31.56K","Price":"9.74","Recom":"-","SMA20":"-0.35%","SMA50":"0.40%","SMA200":"3.13%","Volume":"6,423","Change":"0.62%"}