{"Index":"-","P/E":"6.26","EPS (ttm)":"3.25","Insider Own":"0.20%","Shs Outstand":"82.72M","Perf Week":"20.33%","Market Cap":"1.68B","Forward P/E":"5.95","EPS next Y":"-8.21%","Insider Trans":"-23.76%","Shs Float":"80.43M","Perf Month":"6.93%","Income":"283.00M","PEG":"0.44","EPS next Q":"0.71","Inst Own":"97.90%","Short Float":"13.07%","Perf Quarter":"-10.58%","Sales":"4.44B","P/S":"0.38","EPS this Y":"-36.40%","Inst Trans":"-0.33%","Short Ratio":"13.45","Perf Half Y":"-2.86%","Book/sh":"5.72","P/B":"3.56","ROA":"10.20%","Target Price":"27.00","Perf Year":"-5.17%","Cash/sh":"1.34","P/C":"15.17","EPS next 5Y":"14.30%","ROE":"74.50%","52W Range":"15.01 - 25.78","Perf YTD":"20.40%","Dividend":"-","P/FCF":"12.12","EPS past 5Y":"75.90%","ROI":"22.40%","52W High":"-23.20%","Beta":"2.27","Dividend %":"-","Quick Ratio":"0.80","Sales past 5Y":"2.60%","Gross Margin":"14.70%","52W Low":"31.91%","ATR":"0.82","Employees":"8600","Current Ratio":"1.20","Sales Q/Q":"3.30%","Oper. Margin":"8.30%","RSI (14)":"57.53","Volatility":"5.38% 4.07%","Optionable":"Yes","Debt/Eq":"1.60","EPS Q/Q":"30.00%","Profit Margin":"6.30%","Rel Volume":"0.69","Prev Close":"20.36","Shortable":"Yes","LT Debt/Eq":"1.55","Earnings":"Jul 31 BMO","Payout":"0.00%","Avg Volume":"781.30K","Price":"19.80","Recom":"2.70","SMA20":"12.29%","SMA50":"-3.61%","SMA200":"-3.85%","Volume":"104,477","Change":"-2.75%"}