{"Index":"-","P/E":"-","EPS (ttm)":"-5.54","Insider Own":"0.90%","Shs Outstand":"70.10M","Perf Week":"8.34%","Market Cap":"1.82B","Forward P/E":"-","EPS next Y":"-6.10%","Insider Trans":"-","Shs Float":"61.08M","Perf Month":"-2.66%","Income":"-173.10M","PEG":"-","EPS next Q":"-0.55","Inst Own":"75.90%","Short Float":"1.19%","Perf Quarter":"24.14%","Sales":"14.80M","P/S":"123.01","EPS this Y":"-736.70%","Inst Trans":"3.23%","Short Ratio":"3.45","Perf Half Y":"34.14%","Book/sh":"3.71","P/B":"7.00","ROA":"-105.40%","Target Price":"28.60","Perf Year":"-","Cash/sh":"2.27","P/C":"11.44","EPS next 5Y":"-","ROE":"-678.40%","52W Range":"10.19 - 28.25","Perf YTD":"102.10%","Dividend":"-","P/FCF":"-","EPS past 5Y":"-","ROI":"-","52W High":"-7.26%","Beta":"-","Dividend %":"-","Quick Ratio":"7.80","Sales past 5Y":"-","Gross Margin":"-","52W Low":"157.11%","ATR":"1.44","Employees":"103","Current Ratio":"7.80","Sales Q/Q":"17.60%","Oper. Margin":"-","RSI (14)":"61.57","Volatility":"5.91% 5.76%","Optionable":"Yes","Debt/Eq":"0.02","EPS Q/Q":"25.00%","Profit Margin":"-","Rel Volume":"0.25","Prev Close":"25.97","Shortable":"Yes","LT Debt/Eq":"0.02","Earnings":"Aug 14 BMO","Payout":"-","Avg Volume":"210.59K","Price":"26.20","Recom":"2.40","SMA20":"9.11%","SMA50":"7.54%","SMA200":"31.43%","Volume":"10,701","Change":"0.89%"}