{"Index":"-","P/E":"-","EPS (ttm)":"-0.53","Insider Own":"3.70%","Shs Outstand":"40.47M","Perf Week":"-1.31%","Market Cap":"122.22M","Forward P/E":"-","EPS next Y":"14.60%","Insider Trans":"-","Shs Float":"26.55M","Perf Month":"-10.12%","Income":"-17.60M","PEG":"-","EPS next Q":"-0.11","Inst Own":"7.80%","Short Float":"0.12%","Perf Quarter":"1.68%","Sales":"-","P/S":"-","EPS this Y":"-2.50%","Inst Trans":"10.12%","Short Ratio":"0.46","Perf Half Y":"45.89%","Book/sh":"0.42","P/B":"7.19","ROA":"-93.50%","Target Price":"5.33","Perf Year":"25.83%","Cash/sh":"0.40","P/C":"7.54","EPS next 5Y":"-","ROE":"-134.00%","52W Range":"1.44 - 3.63","Perf YTD":"66.85%","Dividend":"-","P/FCF":"-","EPS past 5Y":"-10.90%","ROI":"-","52W High":"-16.69%","Beta":"0.93","Dividend %":"-","Quick Ratio":"6.40","Sales past 5Y":"-","Gross Margin":"-","52W Low":"109.72%","ATR":"0.13","Employees":"44","Current Ratio":"6.40","Sales Q/Q":"-","Oper. Margin":"-","RSI (14)":"42.44","Volatility":"4.94% 4.17%","Optionable":"No","Debt/Eq":"0.23","EPS Q/Q":"32.00%","Profit Margin":"-","Rel Volume":"0.65","Prev Close":"3.02","Shortable":"Yes","LT Debt/Eq":"0.19","Earnings":"May 09 BMO","Payout":"-","Avg Volume":"69.41K","Price":"3.02","Recom":"1.70","SMA20":"-4.87%","SMA50":"-7.74%","SMA200":"10.77%","Volume":"11,618","Change":"0.00%"}